smstools/transformations/harmonicTransformations.py
smstools/transformations/sineTransformations.py
smstools/transformations/hpsTransformations.py
smstools/transformations/stftTransformations.py
smstools/transformations/stochasticTransformations.py
smstools/models/spsModel.py
smstools/models/sprModel.py
smstools/models/harmonicModel.py
smstools/models/sineModel.py
smstools/models/utilFunctions.py
smstools/models/stft.py
smstools/models/dftModel.py
smstools/models/hpsModel.py
smstools/models/hprModel.py
smstools/models/stochasticModel.py
smstools/models/utilFunctions_C/utilFunctions.h
smstools/models/utilFunctions_C/cutilFunctions.pxd
smstools/models/utilFunctions_C/cutilFunctions.pyx
smstools/models/utilFunctions_C/cutilFunctions.c
smstools/models/utilFunctions_C/utilFunctions.c
smstools/models/utilFunctions_C/utilFunctions_C.cpython-312-darwin.so
sms_tools-1.0.1.dist-info/RECORD
sms_tools-1.0.1.dist-info/WHEEL
sms_tools-1.0.1.dist-info/top_level.txt
sms_tools-1.0.1.dist-info/METADATA
sms_tools-1.0.1.dist-info/licenses/LICENSE
sms_tools-1.0.1.dist-info/licenses/AUTHORS
