Metadata-Version: 2.4
Name: sms-tools
Version: 1.0.1
Summary: Sound analysis/synthesis tools for music applications
Author-email: "Music Technology Group, Universitat Pompeu Fabra" <mtg-info@upf.edu>
Project-URL: Homepage, https://github.com/mtg/sms-tools
Project-URL: Issues, https://github.com/mtg/sms-tools/issues
Classifier: Development Status :: 5 - Production/Stable
Classifier: Intended Audience :: Education
Classifier: Intended Audience :: Science/Research
Classifier: Topic :: Multimedia :: Sound/Audio :: Analysis
Classifier: License :: OSI Approved :: GNU Affero General Public License v3 or later (AGPLv3+)
Requires-Python: >=3.9
License-File: LICENSE
License-File: AUTHORS
Requires-Dist: matplotlib
Requires-Dist: numpy<2.0.0
Requires-Dist: scipy
Dynamic: license-file
